ofxstatement_wise/__init__.py
ofxstatement_wise/wise.py
ofxstatement_transferwise-1.1.0.dist-info/METADATA
ofxstatement_transferwise-1.1.0.dist-info/WHEEL
ofxstatement_transferwise-1.1.0.dist-info/entry_points.txt
ofxstatement_transferwise-1.1.0.dist-info/top_level.txt
ofxstatement_transferwise-1.1.0.dist-info/RECORD
