Metadata-Version: 2.1
Name: ofxstatement-transferwise
Version: 1.1.0
Summary: Transferwise plugin for ofxstatement
Author-email: Andrey Lebedev <andrey@lebedev.lt>
License: GPL-3.0-or-later
Project-URL: Homepage, https://github.com/kedder/ofxstatement-transferwise
Keywords: ofx,banking,statement
Classifier: Development Status :: 3 - Alpha
Classifier: Programming Language :: Python :: 3
Classifier: Natural Language :: English
Classifier: Topic :: Office/Business :: Financial :: Accounting
Classifier: Topic :: Utilities
Classifier: Environment :: Console
Classifier: Operating System :: OS Independent
Requires-Python: >=3.6
Requires-Dist: ofxstatement
